madam/__init__.py
madam/__main__.py
madam/adapters/__init__.py
madam/adapters/agents/__init__.py
madam/adapters/agents/bash.py
madam/adapters/agents/concatenate.py
madam/adapters/agents/ffmpeg.py
madam/adapters/agents/imagemagick.py
madam/adapters/agents/mediainfo.py
madam/adapters/agents/melt.py
madam/adapters/agents/python.py
madam/adapters/agents/scanfolder.py
madam/adapters/agents/scenes.py
madam/adapters/bpmn/__init__.py
madam/adapters/bpmn/assets/BPMN20.xsd
madam/adapters/bpmn/assets/BPMNDI.xsd
madam/adapters/bpmn/assets/DC.xsd
madam/adapters/bpmn/assets/DI.xsd
madam/adapters/bpmn/assets/Semantic.xsd
madam/adapters/bpmn/engine.py
madam/adapters/bpmn/parser.py
madam/adapters/config.py
madam/adapters/interfaces/__init__.py
madam/adapters/interfaces/agents.py
madam/adapters/process/__init__.py
madam/adapters/process/applications.py
madam/adapters/process/docker_api.py
madam/adapters/repository/__init__.py
madam/adapters/repository/applications.py
madam/adapters/repository/assets/migrations/00001.init_tables.rollback.sql
madam/adapters/repository/assets/migrations/00001.init_tables.sql
madam/adapters/repository/jobs.py
madam/adapters/repository/postgresql.py
madam/adapters/repository/timers.py
madam/adapters/repository/watchfolders.py
madam/adapters/repository/workflow_instances.py
madam/adapters/repository/workflows.py
madam/domains/__init__.py
madam/domains/agents.py
madam/domains/application.py
madam/domains/applications.py
madam/domains/entities/__init__.py
madam/domains/entities/agent.py
madam/domains/entities/application.py
madam/domains/entities/constants.py
madam/domains/entities/events.py
madam/domains/entities/job.py
madam/domains/entities/runner.py
madam/domains/entities/timer.py
madam/domains/entities/watchfolder.py
madam/domains/entities/workflow.py
madam/domains/entities/workflow_instance.py
madam/domains/events.py
madam/domains/interfaces/__init__.py
madam/domains/interfaces/agents.py
madam/domains/interfaces/bpmn.py
madam_mam-0.7.3.dist-info/COPYING
madam_mam-0.7.3.dist-info/METADATA
madam_mam-0.7.3.dist-info/WHEEL
madam_mam-0.7.3.dist-info/entry_points.txt
madam_mam-0.7.3.dist-info/RECORD
