Metadata-Version: 2.1
Name: madam-mam
Version: 0.7.3
Summary: MADAM (TM) Multi Agent Digital Asset Manager - a MAM server for Docker Swarm to handle higly distributed media processes
License: GPL-3.0-only
Keywords: BPMN,workflow,media,assets,management,MAM,DAM,docker,swarm
Author: Vincent Texier
Author-email: vit@free.fr
Requires-Python: >=3.8,<4.0
Classifier: License :: OSI Approved :: GNU General Public License v3 (GPLv3)
Classifier: Programming Language :: Python :: 3
Classifier: Programming Language :: Python :: 3.8
Classifier: Programming Language :: Python :: 3.9
Classifier: Programming Language :: Python :: 3.10
Classifier: Programming Language :: Python :: 3.11
Requires-Dist: Jinja2 (>=3.0.1,<4.0.0)
Requires-Dist: PyYAML (==5.1.2)
Requires-Dist: adhesive-zeebe (>=2021.4.3,<2022.0.0)
Requires-Dist: ariadne (>=0.13.0,<0.14.0)
Requires-Dist: docker (>=6.1.0,<7.0.0)
Requires-Dist: lxml (>=4.6.3,<5.0.0)
Requires-Dist: psycopg2-binary (>=2.8.6,<3.0.0)
Requires-Dist: python-sql (>=1.2.2,<2.0.0)
Requires-Dist: rich (>=10.2.2,<11.0.0)
Requires-Dist: timecode (>=1.3.1,<2.0.0)
Requires-Dist: uvicorn (>=0.14.0,<0.15.0)
Requires-Dist: watchgod (>=0.7,<0.8)
Requires-Dist: yoyo-migrations (>=8.2.0,<9.0.0)
